[
  {
    "名词": "巻煙草",
    "解释": "卷煙草（まきたばこ）指纸卷香烟，明治时期随西洋文化传入日本。此前日本以烟管（キセル）吸食刻烟为主，明治开国后纸卷烟因携带方便、燃烧持久而迅速普及，成为近代化与西洋文明的象征之一。",
    "书中原文": "「主人は巻煙草の灰を火桶の中へはたき落す」",
    "网络来源": "https://zh.wikipedia.org/wiki/香烟"
  },
  {
    "名词": "縮緬",
    "解释": "縮緬（ちりめん）是日本传统丝绸织物，表面因强捻纬纱与弱捻经纱交织而形成细密皱纹。明治时期缩緬广泛用于高级和服、腰带及工艺品，京都丹后地区为主要产地。",
    "书中原文": "「かの鋭どい声の所有主は縮緬の二枚重ねを畳へ擦り付けながら這入って来る」",
    "网络来源": "https://baike.baidu.com/item/缩缅/1040386"
  },
  {
    "名词": "招魂社",
    "解释": "招魂社（しょうこんしゃ）是日本为祭祀战殁者而建立的神社。1869年（明治2年）设立东京招魂社（祭祀戊辰战争战死者），1879年改称靖国神社。此后各地也设立了类似的招魂社，1939年统一改称护国神社。",
    "书中原文": "「三坪ほどの小庭へ招魂社の石灯籠を移した時のごとく」",
    "网络来源": "https://zh.wikipedia.org/wiki/靖国神社"
  },
  {
    "名词": "西洋館",
    "解释": "西洋館（せいようかん）指明治时期日本建造的西洋风格建筑。明治政府推动文明开化，聘请外国建筑师（如Josiah Conder）设计鹿鳴館、旧岩崎邸等。地方工匠也创造出独特的\"拟洋风建筑\"，成为日本近代化在建筑领域的标志。",
    "书中原文": "「あの大きな西洋館の倉のあるうちですか」",
    "网络来源": "https://zh.wikipedia.org/wiki/旧岩崎邸庭園"
  },
  {
    "名词": "標札",
    "解释": "標札（ひょうさつ）即门牌、姓名牌，悬挂于日本家庭门口以标示姓氏。明治时期近代邮政制度建立后，为方便邮递员投递而逐步普及，成为日本独特的门牌文化，也承载着日本的姓氏文化与社会认同。",
    "书中原文": "「金田と云う標札が出ていますな」",
    "网络来源": "https://baike.baidu.com/item/门牌/10703311"
  },
  {
    "名词": "実業家",
    "解释": "実業家指明治时期兴起的实业家/企业家阶层。明治政府推行殖产兴业政策，涌现出岩崎弥太郎（三菱财阀）、涩泽荣一（日本资本主义之父）等人物。他们引进股份公司制度，推动了日本资本主义工业化的快速发展。",
    "书中原文": "「元来ここの主人は博士とか大学教授とかいうと非常に恐縮する男であるが、妙な事には実業家に対する尊敬の度は極めて低い」",
    "网络来源": "https://www.nippon.com/cn/japan-topics/b06903/"
  },
  {
    "名词": "園遊会",
    "解释": "園遊会（えんゆうかい）指日本皇室主办的花园宴会。明治时期由外务卿井上馨提议，仿照英国王室 garden party 于1880年创设\"赏菊会\"、1881年创设\"赏樱会\"，每年春秋在赤坂御用地等处举办，招待外国使节与各界名流，展示文明开化成果。",
    "书中原文": "「この間なんざ園遊会へおいでになった」",
    "网络来源": "https://zh.wikipedia.org/wiki/园游会_(日本皇室)"
  },
  {
    "名词": "男爵",
    "解释": "男爵（だんしゃく）是日本华族制度五等爵位中的最末一等。1884年（明治17年）颁布《华族令》，将华族分为公爵至男爵五等，世袭爵位。男爵主要包括旧公卿分家、维新功臣中功绩相对较低者及神职世袭家等。",
    "书中原文": "「牧山男爵さ」",
    "网络来源": "https://zh.wikipedia.org/wiki/华族_(日本)"
  },
  {
    "名词": "大島紬",
    "解释": "大島紬（おおしまつむぎ）是日本鹿儿岛县奄美大岛出产的高级绢织物，以独特的泥染工艺和絣织技术闻名。明治时期生产技术普及化，从贵族专享走向大众，并引入西方染色技术和织布机提升品质。被指定为国家重要无形文化财产。",
    "书中原文": "「迷亭は大島紬に古渡更紗か何か重ねてすましている」",
    "网络来源": "https://zh.wikipedia.org/wiki/大島紬"
  },
  {
    "名词": "古渡更紗",
    "解释": "古渡更紗（こわたりさらさ）指17至18世纪（江户前期）经南蛮贸易从印度传入日本的印花棉布。其色彩鲜艳、图案异国情调浓厚，深受大名武士喜爱，用于阵羽织、小袖、烟管袋等。明治时期仍是珍贵的古董纺织品，是跨文化交流的物质见证。",
    "书中原文": "「迷亭は大島紬に古渡更紗か何か重ねてすましている」",
    "网络来源": "https://zh.wikipedia.org/wiki/更紗"
  },
  {
    "名词": "鉄枴仙人",
    "解释": "鉄枴仙人（てっかいせんにん）即铁拐李（李铁拐），中国道教八仙之一。传说本名李玄，灵魂出窍随太上老君西游，归来时尸身被焚，只得借饿莩还魂，从此蓬头跛足，拄铁拐行走。元代画家颜辉所作《李仙像》藏于日本京都智恩院，对日本室町时代绘画影响深远。",
    "书中原文": "「鉄枴仙人が軍鶏の蹴合いを見るような顔をして平気で聞いている」",
    "网络来源": "https://baike.baidu.com/item/铁拐李/3185"
  },
  {
    "名词": "鼎坐",
    "解释": "鼎坐（ていざ）意为三人如鼎之三足般相对而坐。鼎是古代中国三足青铜器，王权象征。由此衍生出\"鼎坐\"（三人对坐）、\"鼎立\"（三方对峙）、\"鼎谈\"（三人座谈）等词汇。此处描写主客三人沉默相对的场景。",
    "书中原文": "「しばらくは三人鼎坐のまま無言である」",
    "网络来源": "https://baike.baidu.com/item/鼎/10566888"
  },
  {
    "名词": "軍配団扇",
    "解释": "軍配団扇（ぐんばいうちわ）原为战国时代武将或军师在战场上指挥部队所用之扇，以皮或铁制成，兼作防具。表面绘有十干十二支、二十八宿等图案，亦用于占卜吉凶。现代主要作为大相扑行司裁定胜负的道具，\"军配を上げる\"已成为宣告胜利的习惯用语。",
    "书中原文": "「迷亭は双方の間に坐って、銀煙管を軍配団扇のように持って」",
    "网络来源": "https://zh.wikipedia.org/wiki/軍配"
  },
  {
    "名词": "格子戸",
    "解释": "格子戸（こうしど）是日本传统建筑中用木条或竹条组合成格子状的拉门或推门，常见于町家（商家住宅）正面。兼具采光、通风、隐私保护与装饰功能。明治时期随着玻璃窗的引入，格子戸与玻璃窗结合使用，是日本传统建筑的重要元素。",
    "书中原文": "「折柄格子戸のベルが飛び上るほど鳴って」",
    "网络来源": "https://baike.baidu.com/item/格子门/3956639"
  },
  {
    "名词": "火桶",
    "解释": "火桶（ひおけ）是日本传统的取暖器具，形似木桶，内放炭火。明治时期，火桶常用于掘り炬燵（在床下挖洞嵌入火桶的暖炉）或作为手炉使用。热源多为木炭或炭团，是近代电气化之前日本家庭冬季不可或缺的暖具。",
    "书中原文": "「主人は巻煙草の灰を火桶の中へはたき落す」",
    "网络来源": "https://baike.baidu.com/item/被炉/9961032"
  },
  {
    "名词": "八卦",
    "解释": "八卦（はっけ）源自中国《易经》的八种基本卦象（乾兑离震巽坎艮坤），用于占卜吉凶。明治时代日本易学大师高岛吞象（1832-1914）著《高岛易断》，将八卦占卜应用于军政大事，在日本有\"易圣\"之称。此处迷亭心中默念八卦，带有调侃意味。",
    "书中原文": "「迷亭は双方の間に坐って、銀煙管を軍配団扇のように持って、心の裡で八卦よいやよいやと怒鳴っている」",
    "网络来源": "https://baike.baidu.com/item/八卦/10087"
  },
  {
    "名词": "縁辺",
    "解释": "縁辺（えんぺん/えんぴん）指婚姻关系、亲事、姻缘。明治时期婚姻多通过媒人介绍（媒酌结婚），且明治民法规定结婚须经户主同意，维护了家制度下的婚姻秩序。此处鼻子称女儿的\"縁辺之事\"，指金田家女儿的婚事安排。",
    "书中原文": "「たしか娘の縁辺の事につきましてもいろいろ牧山さまへ御心配を願いましたそうで」",
    "网络来源": "https://baike.baidu.com/item/姻缘/11015218"
  },
  {
    "名词": "金剛石",
    "解释": "金剛石（こんごうせき）即钻石，日语古称。明治时期西洋宝石文化随文明开化传入日本，钻石开始用于皇室首饰（如明治蒂亚拉）和上流社会的戒指首饰。日本本土不产宝石级钻石，明治时期的钻石多从欧洲进口。",
    "书中原文": "「金剛石入りの指環の嵌った指を、膝の上へ併べて」",
    "网络来源": "https://baike.baidu.com/item/金刚石/45251"
  },
  {
    "名词": "軍鶏",
    "解释": "軍鶏（しゃも）是日本传统的斗鸡品种，名称源自泰国旧称\"シャム\"（Siam）。江户初期从东南亚传入，经长期选育形成多个品种，其中7种被指定为国家天然纪念物。明治时期仍有斗鸡风俗。此处描写迷亭如铁拐仙观斗鸡般悠然旁观争吵。",
    "书中原文": "「鉄枴仙人が軍鶏の蹴合いを見るような顔をして平気で聞いている」",
    "网络来源": "https://baike.baidu.com/item/军鸡/10703193"
  },
  {
    "名词": "付け文",
    "解释": "付け文（つけぶみ）是日本古语，指悄悄送给异性的情书、求爱信。平安时代贵族恋爱中，后朝の文（次日清晨送出的感谢信）是必不可少的礼仪。明治时期的小说中仍使用此古雅语，带有古典浪漫色彩。此处迷亭调侃寒月是否向金田小姐送了情书。",
    "书中原文": "「寒月が御嬢さんに付け文でもしたんですか」",
    "网络来源": "https://zh.wiktionary.org/wiki/付け文"
  },
  {
    "名词": "新道",
    "解释": "新道（しんみち）指新开辟的道路或街区。明治时期东京近代化过程中，市区改正事业新修了大量道路，形成诸多被称为\"新道\"的街区。在小说中特指一条具体街巷，住着二弦琴师傅，反映了明治时代东京城市发展中的地名文化。",
    "书中原文": "「車屋ばかりじゃありません。新道の二絃琴の師匠からも大分いろいろな事を聞いています」",
    "网络来源": "https://baike.baidu.com/item/神田须田町/16277319"
  },
  {
    "名词": "石灯籠",
    "解释": "石灯籠（いしどうろう）是日本庭园和神社寺院中的传统石制灯具，源自中国佛教供灯，经朝鲜传入日本。奈良时代出现于寺院，安土桃山时代随茶道发展进入茶庭露地，江户时代成为庭园必备设施。明治时期继续作为回游式庭园的重要点缀。",
    "书中原文": "「三坪ほどの小庭へ招魂社の石灯籠を移した時のごとく」",
    "网络来源": "https://baike.baidu.com/item/石灯笼/9355718"
  }
]