[
  {
    "名词": "chiffarobe",
    "分类": "物件",
    "解释": "一种组合式家具，兼具衣柜（挂衣空间）和抽屉柜（折叠衣物收纳）功能的橱柜。该词由chiffonier（小衣柜）与wardrobe（衣柜）两词融合而成，20世纪初在美国家庭，尤其是美国南方（缺少内置壁橱的小户型住宅）中广泛流行。在《杀死一只知更鸟》中，汤姆·罗宾逊被指控为梅耶拉·尤厄尔\"砸开一个chiffarobe\"。",
    "书中原文": "I said come here, nigger, and bust up this chiffarobe for me, I gotta nickel for you.",
    "网络来源": "https://en.m.wikipedia.org/wiki/Chifforobe"
  },
  {
    "名词": "Mr. Jingle",
    "分类": "人物",
    "解释": "查尔斯·狄更斯首部小说《匹克威克外传》（The Pickwick Papers）中的虚构角色，全名阿尔弗雷德·金格尔（Alfred Jingle）。他是一个快言快语、巧舌如簧的流浪骗子和巡回演员，以其碎片化、断断续续的独特说话方式著称。在《杀死一只知更鸟》中，斯库特用Mr. Jingle来类比梅耶拉说话的方式。",
    "书中原文": "Mayella sounded like a Mr. Jingle in a book I had been reading.",
    "网络来源": "https://en.wikipedia.org/wiki/Mr_Jingle"
  }
]